<?xml version="1.0" encoding="UTF-8"?>
<kmodule xmlns:xsi="http://www.w3.org/2001/XMLSchema-instance"
         xmlns="http://jboss.org/kie/6.0.0/kmodule">

	<kbase name="HelloWorldKB" packages="ssii.drools.helloworld">
        <ksession name="HelloWorldKS"/>
    </kbase>
    
    <kbase name="HonestPoliticianKB" packages="ssii.drools.honestpolitician">
        <ksession name="HonestPoliticianKS"/>
    </kbase>

    <kbase name="ShoppingKB" packages="ssii.drools.shopping">
        <ksession name="ShoppingKS"/>
    </kbase>

    
</kmodule>